[
    {
        "QC": "Is data present?",
        "full_name": "expect_column_values_to_not_be_null",
        "total_variables": 59,
        "failed_variables": 49,
        "passed_variables": 10,
        "complete_variables_percentage": 16.95,
        "missing_variables_percentage": 83.05,
        "total_patients": 1,
        "failed_patients": 1,
        "passed_patients": 0,
        "complete_patients_percentage": 0.0,
        "missing_patients_percentage": 100.0,
        "total_quality_checks": 59,
        "failed_quality_checks": 49,
        "passed_quality_checks": 10,
        "quality_checks_percentage_pass": 16.95,
        "quality_checks_percentage_fail": 83.05,
        "full_dm_total_variables": 203,
        "full_dm_failed_variables": 193,
        "full_dm_passed_variables": 10,
        "full_dm_complete_variables_percentage": 4.93,
        "full_dm_missing_variables_percentage": 95.07
    }
]